endmapper/__init__.py
endmapper/endpoint_handlers.py
endmapper/urls.py
endmapper/mappers/__init__.py
endmapper/mappers/base_mapper.py
endmapper/mappers/django_mapper.py
endmapper/mappers/fastapi_mapper.py
endmapper-0.5.4.dist-info/LICENSE
endmapper-0.5.4.dist-info/METADATA
endmapper-0.5.4.dist-info/WHEEL
endmapper-0.5.4.dist-info/top_level.txt
endmapper-0.5.4.dist-info/RECORD
